{"config_id": "e15331acc3f0a5c0", "default_version": "madx", "files": {"madx": {"sha1": "4107c7e67443b32c1e21092982e45ba1f85addfb", "sha256": "5ff775a380a5ae400c24c86c59f0f0b8ae739d50a70822f0dc3d46e7663a6882", "url": "https://public.ukp.informatik.tu-darmstadt.de/AdapterHub/text_lang/tk/xlm-roberta-large/pfeiffer/tk_relu_2.zip"}}, "info": {"adapter_config": {"adapter_residual_before_ln": false, "ln_after": false, "ln_before": false, "mh_adapter": false, "non_linearity": "relu", "original_ln_after": true, "original_ln_before": true, "output_adapter": true, "reduction_factor": 2, "residual_before_ln": true}, "adapter_id": "@ukp/xlm-roberta-large-tk-wiki_pfeiffer", "model_name": "xlm-roberta-large", "sha1_checksum": "4107c7e67443b32c1e21092982e45ba1f85addfb", "source": "ah", "subtask": "wiki", "task": "tk", "username": "ukp"}}